linqpy
