Metadata-Version: 1.1
Name: linqpy
Version: 0.3.1
Summary: Simple implementation of .NET Linq in python list.
Home-page: https://github.com/danielblando/linqpy
Author: Daniel Blando
Author-email: daniel@blando.com.br
License: MIT
Keywords: linq c# .net list
Platform: UNKNOWN
Classifier: Development Status :: 4 - Beta
Classifier: Intended Audience :: Developers
Classifier: License :: OSI Approved :: MIT License
Classifier: Operating System :: OS Independent
Classifier: Programming Language :: Python
Classifier: Programming Language :: Python :: 2.7
Classifier: Topic :: Software Development :: Libraries :: Python Modules
Classifier: Topic :: Internet
